[
  {
    "ContainingType": "BasicAPI.Features.Auth.LicenseController",
    "Method": "Post",
    "RelativePath": "License",
    "HttpMethod": "POST",
    "IsController": true,
    "Order": 0,
    "Parameters": [
      {
        "Name": "model",
        "Type": "BasicAPI.Features.Auth.License",
        "IsRequired": true
      }
    ],
    "ReturnTypes": [
      {
        "Type": "BasicAPI.Features.Auth.License",
        "MediaTypes": [
          "text/plain",
          "application/json",
          "text/json"
        ],
        "StatusCode": 200
      }
    ],
    "EndpointName": "CreateLicense"
  },
  {
    "ContainingType": "BasicAPI.Controllers.WeatherForecastController",
    "Method": "Get",
    "RelativePath": "WeatherForecast",
    "HttpMethod": "GET",
    "IsController": true,
    "Order": 0,
    "Parameters": [],
    "ReturnTypes": [
      {
        "Type": "System.Collections.Generic.IEnumerable\u00601[[BasicAPI.WeatherForecast, BasicAPI, Version=1.0.0.0, Culture=neutral, PublicKeyToken=null]]",
        "MediaTypes": [
          "text/plain",
          "application/json",
          "text/json"
        ],
        "StatusCode": 200
      }
    ],
    "EndpointName": "GetWeatherForecast"
  }
]